{
    "chart": {
        "null": null,
        "100025": 27,
        "100026": 117,
        "100027": 52
    },
    "images": [
        "https://sirekap-obj-formc.kpu.go.id/c4ec/pemilu/ppwp/32/06/01/20/01/3206012001005-20240214-155833--1a492382-932f-48e3-8c5a-9e33451663d5.jpg",
        "https://sirekap-obj-formc.kpu.go.id/c4ec/pemilu/ppwp/32/06/01/20/01/3206012001005-20240215-142834--1378c6a2-01f1-4cfd-856a-33d3724258c6.jpg",
        "https://sirekap-obj-formc.kpu.go.id/c4ec/pemilu/ppwp/32/06/01/20/01/3206012001005-20240215-144934--5e90f2c6-c51d-4fb5-89ae-8849055b1610.jpg"
    ],
    "administrasi": {
        "suara_sah": 196,
        "suara_total": 201,
        "pemilih_dpt_j": 277,
        "pemilih_dpt_l": 141,
        "pemilih_dpt_p": 136,
        "pengguna_dpt_j": 196,
        "pengguna_dpt_l": 93,
        "pengguna_dpt_p": 103,
        "pengguna_dptb_j": 4,
        "pengguna_dptb_l": 3,
        "pengguna_dptb_p": 1,
        "suara_tidak_sah": 5,
        "pengguna_total_j": 201,
        "pengguna_total_l": 97,
        "pengguna_total_p": 104,
        "pengguna_non_dpt_j": 1,
        "pengguna_non_dpt_l": 1,
        "pengguna_non_dpt_p": 0
    },
    "psu": null,
    "ts": "2024-02-16 06:00:27",
    "status_suara": true,
    "status_adm": true
}