{
    "chart": null,
    "images": [
        "https://sirekap-obj-formc.kpu.go.id/11a3/pemilu/ppwp/32/74/05/10/02/3274051002020-20240216-033832--85bb66a8-1184-48f8-8e13-3e05e8c3e49a.jpg",
        null,
        "https://sirekap-obj-formc.kpu.go.id/11a3/pemilu/ppwp/32/74/05/10/02/3274051002020-20240216-033838--d8f3ee91-e212-4a82-8ea3-a47c8e2b6db8.jpg"
    ],
    "administrasi": {
        "suara_sah": 210,
        "suara_total": 220,
        "pemilih_dpt_j": 250,
        "pemilih_dpt_l": 129,
        "pemilih_dpt_p": 121,
        "pengguna_dpt_j": 215,
        "pengguna_dpt_l": 108,
        "pengguna_dpt_p": 107,
        "pengguna_dptb_j": 4,
        "pengguna_dptb_l": 3,
        "pengguna_dptb_p": 1,
        "suara_tidak_sah": 10,
        "pengguna_total_j": 220,
        "pengguna_total_l": 112,
        "pengguna_total_p": 108,
        "pengguna_non_dpt_j": 1,
        "pengguna_non_dpt_l": 1,
        "pengguna_non_dpt_p": 0
    },
    "psu": null,
    "ts": "2024-02-16 04:00:27",
    "status_suara": false,
    "status_adm": true
}